{
  "routes": [
    {
      "id": 1,
      "name": "Braslav",
      "image": "beautiful-landscape.jpg"
    },
    {
      "id": 2,
      "name": "Mir",
      "image": "beautiful-landscape.jpg"
    },
    {
      "id": 3,
      "name": "Hesvizh",
      "image": "beautiful-landscape.jpg"
    }
  ],
  "companions": [
    {
      "id": 1,
      "name": "Maks"
    },
    {
      "id": 2,
      "name": "Evelina"
    },
    {
      "id": 3,
      "name": "Bob"
    },
    {
      "id": 4,
      "name": "Nike"
    }
  ]
}
